slave.sv
module slave (
  input [0:0] PCLK,
  input [0:0] PRESET,
  input [0:0] PSEL,
  input [0:0] PENABLE,
  input [0:0] PWRITE,
  input [31:0] PRWADDR,     // Master Out, Slave In
  input [31:0] PRWDATA,
  output reg [31:0] PRDATA1,   // Master In, Slave Out
  output reg [0:0] PREADY   // Slave PREADY
);

reg [3:0] state;    // Состояние конечного автомата
reg [31:0] memory [0:127];
reg [2:0] c;

always @(PRESET) begin

if (PRESET == 1'b1) begin
  // Сброс в начальное состояние
  state <= 4'b0000;
  PRDATA1 <= 32'b00000000000000000000000000000000;

  PREADY = 0;


end
end

// Логика конечного автомата
always @(posedge PCLK or posedge PRESET) begin

if (PRESET) begin
  // Сброс в начальное состояние
  state <= 4'b0000;
  PRDATA1 <= 32'b00000000000000000000000000000000;
end else begin  
  
  $display("in slave");

  if(PSEL == 1'b1 && PENABLE == 1'b0 && PWRITE == 1'b0) begin 
    $display("if1");
    PREADY = 0; 
  end
    
  else if(PSEL == 1'b1 && PENABLE == 1'b1 && PWRITE == 1'b0) begin 
    $display("wriite in slave");
    PRDATA1 <= memory[PRWADDR];
    PREADY = 1;
  end

  else if(PSEL == 1'b1 && PENABLE == 1'b0 && PWRITE == 1'b1) begin 
    $display("if2");
    PREADY = 0; 
  end

  else if(PSEL == 1'b1 && PENABLE == 1'b1 && PWRITE == 1'b1) begin 
    $display("if3");
    PREADY = 1;
    PRDATA1 <= PRWDATA;
    memory[PRWADDR] <= PRWDATA;
    c = c + 1;
  end

  else begin
    PREADY = 0;
    $display("if4");
  end

  end
end
endmodule

master.sv
module master (
  input [0:0] PCLK,
  input [0:0] PRESET,

  input [0:0] PSEL,
  input [0:0] PREADY,
  input [0:0] transfer,

  input [0:0] PWRITE,
  input [31:0] PADDR,
  input [31:0] PDATA, 
  output reg [0:0] PENABLE,
  output reg [31:0] PRWDATA,
  output reg [31:0] PRWADDR
);

// Регистры для хранения данных (можно добавить)
reg [31:0] memory [0:127];
reg [1:0] state = 2'b00;

// переделать в таск, для упрощения работы
task apb_read;
//input [31:0] data;
input [31:0] addr;
  begin
    //PRWDATA <= memory[addr];
    PRWDATA <= PDATA;
    //PRWDATA <= data;
    PRWADDR <= addr;
  end
endtask

task apb_write;
input [31:0] addr;
input [31:0] data;
  begin
    //memory[addr] <= data;
    PRWDATA <= data;
    PRWADDR <= addr;
  end
endtask

integer i;
reg [31:0] temp;

always @(posedge PCLK or posedge PRESET or posedge PENABLE) begin

  if (PRESET == 1'b1) begin 
    PRWDATA <= 0;
    PRWADDR <= 0;
    state = 2'b00;
    $display("PRESET");
  end

  case (state)
  2'b00:
  begin

    $display("state 00");

    //else begin
      //$display("(PSEL == 1'b1 && PENABLE == 1'b0)");
    PENABLE = 1'b0;
    if (PSEL == 1'b1 && transfer == 1'b1) begin 
    //$display("if accepted");
      if (PWRITE == 1'b1) begin
        state <= 2'b01;
      end
      else begin
        state <= 2'b10;
      end
    end
    //end
  end
  2'b01:
  begin
    PENABLE = 1'b1;
    $display("state 01 PWRITE");
    if (PSEL == 1'b1 && transfer == 1'b1 && PREADY == 1'b1) begin
      $display("PWRITE");
      apb_write(PADDR,PDATA);
      state <= 2'b11;
      $display("master end");
    end

  end
  2'b10:
  begin
    $display("state 10 read");
    PENABLE <= 1'b1;
    if (PSEL == 1'b1 && transfer == 1'b1 && PREADY == 1'b1) begin
      $display("read");
      apb_read(PADDR);
      state <= 2'b11;
    end

  end
  2'b11:begin
    $display("state 11");

    if (PSEL == 1'b1 && transfer == 1'b1 && PREADY == 1'b1) begin
      $display("go to PWRITE or read from acces");
      //apb_read(PADDR);
      if (PWRITE == 1'b1) begin
        state <= 2'b01;
      end
      else begin
        state <= 2'b10;
      end
    end

    if (PSEL == 1'b1 && transfer == 1'b0 && PREADY == 1'b1) begin
      $display("");
      //apb_read(PADDR);
      state <= 2'b00;
    end
    
  end
  default: begin
    //$display("no state");
  end
  endcase
end
endmodule
// изменить на PADDR и типо того

testbench.sv
`include "master.sv"
`include "slave.sv"

module testbench;

reg [0:0] PCLK;
reg [0:0] PRESET;

reg [0:0] PSEL;
reg [0:0] transfer;
reg [0:0] r;
reg [0:0] PWRITE;

reg [31:0] PADDR;
reg [31:0] PDATA;

wire [0:0] PENABLE;
wire [31:0] PRWDATA;
wire [31:0] PRWADDR;

wire [31:0] PRDATA1;
wire [0:0] PREADY;

master m (
  .PCLK(PCLK),
  .PRESET(PRESET),
  .PSEL(PSEL),
  .PREADY(PREADY),
  .transfer(transfer),
  .PWRITE(PWRITE),   
  .PADDR(PADDR),
  .PDATA(PDATA),

  .PENABLE(PENABLE),
  .PRWDATA(PRWDATA),
  .PRWADDR(PRWADDR)
);

slave s (
  .PCLK(PCLK),
  .PRESET(PRESET),
  .PSEL(PSEL),
  .PENABLE(PENABLE),
  .PWRITE(PWRITE),

  .PRWDATA(PRWDATA), // master out, slave in data
  .PRWADDR(PRWADDR), // master out, slava in addr

  .PRDATA1(PRDATA1),    // slave out data
  .PREADY(PREADY)    
);

initial begin

  $display("start");
  $dumpfile("testbench.vcd");
  $dumpvars(0,testbench);
  PADDR = 32'b00000000000000000000000000000000;
  PDATA = 32'h00000309;

  PWRITE = 1'b1;
  
  PCLK = 1'b0;
  PRESET = 0;
  PSEL = 0;
  transfer = 1'b1;

  PRESET = 1;
  #10;
  PRESET = 0;
  PSEL = 1;
  #40;
  PSEL = 0;
  #20;

  PADDR = 32'b00000000000000000000000000000100;
  PDATA = 32'h07122023;
  PSEL = 1;
  #40;
  PSEL = 0;
  #20;

  PADDR = 32'b0000_0000_0000_0000_0000_0000_0000_1000;
  PDATA = 32'h4d4f544f;
  PSEL = 1;
  #40;
  PSEL = 0;
  #20;

  PADDR = 32'b000000000000000000000000001100;
  PDATA = 32'h4d415849;
  PSEL = 1;
  #40;
  PSEL = 0;
  #20;

  $finish;
end

always begin
  #5 PCLK = ~PCLK;
end

endmodule

testbench.vcd
$date
	Wed Dec 20 23:01:44 2023
$end
$version
	Icarus Verilog
$end
$timescale
	1s
$end
$scope module testbench $end
$var wire 32 ! PRWDATA [31:0] $end
$var wire 32 " PRWADDR [31:0] $end
$var wire 1 # PREADY $end
$var wire 32 $ PRDATA1 [31:0] $end
$var wire 1 % PENABLE $end
$var reg 32 & PADDR [31:0] $end
$var reg 1 ' PCLK $end
$var reg 32 ( PDATA [31:0] $end
$var reg 1 ) PRESET $end
$var reg 1 * PSEL $end
$var reg 1 + PWRITE $end
$var reg 1 , transfer $end
$scope module m $end
$var wire 32 - PADDR [31:0] $end
$var wire 1 ' PCLK $end
$var wire 32 . PDATA [31:0] $end
$var wire 1 ) PRESET $end
$var wire 1 * PSEL $end
$var wire 1 + PWRITE $end
$var wire 1 , transfer $end
$var wire 1 # PREADY $end
$var reg 1 % PENABLE $end
$var reg 32 / PRWADDR [31:0] $end
$var reg 32 0 PRWDATA [31:0] $end
$var reg 2 1 state [1:0] $end
$scope task apb_read $end
$var reg 32 2 addr [31:0] $end
$upscope $end
$scope task apb_write $end
$var reg 32 3 addr [31:0] $end
$var reg 32 4 data [31:0] $end
$upscope $end
$upscope $end
$scope module s $end
$var wire 1 ' PCLK $end
$var wire 1 % PENABLE $end
$var wire 1 ) PRESET $end
$var wire 32 5 PRWADDR [31:0] $end
$var wire 32 6 PRWDATA [31:0] $end
$var wire 1 * PSEL $end
$var wire 1 + PWRITE $end
$var reg 32 7 PRDATA1 [31:0] $end
$var reg 1 # PREADY $end
$var reg 3 8 c [2:0] $end
$var reg 4 9 state [3:0] $end
$upscope $end
$upscope $end
$enddefinitions $end
$comment Show the parameter values. $end
$dumpall
$end
#0
$dumpvars
b0 9
bx 8
b0 7
b0 6
b0 5
bx 4
bx 3
bx 2
b0 1
b0 0
b0 /
b1100001001 .
b0 -
1,
1+
0*
1)
b1100001001 (
0'
b0 &
0%
b0 $
0#
b0 "
b0 !
$end
#5
1'
#10
0'
1*
0)
#15
b1 1
1'
#20
0'
#25
1%
1'
#30
0'
#35
b11 1
b1100001001 !
b1100001001 0
b1100001001 6
b1100001001 4
b0 3
1#
1'
#40
0'
#45
b1 1
b1100001001 $
b1100001001 7
1'
#50
0'
0*
#55
0#
1'
#60
0'
#65
1'
#70
0'
1*
b111000100100010000000100011 (
b111000100100010000000100011 .
b100 &
b100 -
#75
b11 1
b100 "
b100 /
b100 5
b111000100100010000000100011 !
b111000100100010000000100011 0
b111000100100010000000100011 6
b111000100100010000000100011 4
b100 3
1#
1'
#80
0'
#85
b1 1
b111000100100010000000100011 $
b111000100100010000000100011 7
1'
#90
0'
#95
b11 1
1'
#100
0'
#105
b1 1
1'
#110
0'
0*
#115
0#
1'
#120
0'
#125
1'
#130
0'
1*
b1000100010011110100110001011010 (
b1000100010011110100110001011010 .
b1000 &
b1000 -
#135
b11 1
b1000 "
b1000 /
b1000 5
b1000100010011110100110001011010 !
b1000100010011110100110001011010 0
b1000100010011110100110001011010 6
b1000100010011110100110001011010 4
b1000 3
1#
1'
#140
0'
#145
b1 1
b1000100010011110100110001011010 $
b1000100010011110100110001011010 7
1'
#150
0'
#155
b11 1
1'
#160
0'
#165
b1 1
1'
#170
0'
0*
#175
0#
1'
#180
0'
#185
1'
#190
0'
1*
b1000100010001010100111001001001 (
b1000100010001010100111001001001 .
b1100 &
b1100 -
#195
b11 1
b1100 "
b1100 /
b1100 5
b1000100010001010100111001001001 !
b1000100010001010100111001001001 0
b1000100010001010100111001001001 6
b1000100010001010100111001001001 4
b1100 3
1#
1'
#200
0'
#205
b1 1
b1000100010001010100111001001001 $
b1000100010001010100111001001001 7
1'
#210
0'
#215
b11 1
1'
#220
0'
#225
b1 1
1'
#230
0'
0*
#235
0#
1'
